LICENSE
MANIFEST.in
Makefile
README.rst
pyproject.toml
setup.py
GBTparser.egg-info/PKG-INFO
GBTparser.egg-info/SOURCES.txt
GBTparser.egg-info/dependency_links.txt
GBTparser.egg-info/entry_points.txt
GBTparser.egg-info/requires.txt
GBTparser.egg-info/top_level.txt
cantools/__init__.py
cantools/__main__.py
cantools/compat.py
cantools/errors.py
cantools/j1939.py
cantools/logreader.py
cantools/tester.py
cantools/typechecking.py
cantools/version.py
cantools/autosar/__init__.py
cantools/autosar/end_to_end.py
cantools/autosar/secoc.py
cantools/autosar/snakeauth.py
cantools/database/__init__.py
cantools/database/errors.py
cantools/database/utils.py
cantools/database/can/__init__.py
cantools/database/can/attribute.py
cantools/database/can/attribute_definition.py
cantools/database/can/bus.py
cantools/database/can/c_source.py
cantools/database/can/database.py
cantools/database/can/environment_variable.py
cantools/database/can/internal_database.py
cantools/database/can/message.py
cantools/database/can/node.py
cantools/database/can/signal.py
cantools/database/can/signal_group.py
cantools/database/can/formats/__init__.py
cantools/database/can/formats/dbc.py
cantools/database/can/formats/dbc_specifics.py
cantools/database/can/formats/kcd.py
cantools/database/can/formats/sym.py
cantools/database/can/formats/utils.py
cantools/database/can/formats/arxml/__init__.py
cantools/database/can/formats/arxml/bus_specifics.py
cantools/database/can/formats/arxml/database_specifics.py
cantools/database/can/formats/arxml/ecu_extract_loader.py
cantools/database/can/formats/arxml/end_to_end_properties.py
cantools/database/can/formats/arxml/message_specifics.py
cantools/database/can/formats/arxml/node_specifics.py
cantools/database/can/formats/arxml/secoc_properties.py
cantools/database/can/formats/arxml/system_loader.py
cantools/database/can/formats/arxml/utils.py
cantools/database/diagnostics/__init__.py
cantools/database/diagnostics/data.py
cantools/database/diagnostics/database.py
cantools/database/diagnostics/did.py
cantools/database/diagnostics/internal_database.py
cantools/database/diagnostics/formats/__init__.py
cantools/database/diagnostics/formats/cdd.py
gbtparser.egg-info/PKG-INFO
gbtparser.egg-info/SOURCES.txt
gbtparser.egg-info/dependency_links.txt
gbtparser.egg-info/entry_points.txt
gbtparser.egg-info/requires.txt
gbtparser.egg-info/top_level.txt
