Metadata-Version: 2.1
Name: gbtparser
Version: 1.0.8
Summary: GBT CAN bus parser
Home-page: https://github.com/AnandSingh-Euler/GBT-parser
Author: Anand Singh
Author-email: anandsingh16898@gmail.com
License: MIT
Keywords: GBT,can,can bus,dbc,automotive
Classifier: License :: OSI Approved :: MIT License
Requires-Python: >=3.8
Provides-Extra: plot
Provides-Extra: windows-all
License-File: LICENSE
